dbos_openai_agents/__init__.py
dbos_openai_agents/runner.py
dbos_openai_agents-0.2.0.dist-info/METADATA
dbos_openai_agents-0.2.0.dist-info/WHEEL
dbos_openai_agents-0.2.0.dist-info/licenses/LICENSE
dbos_openai_agents-0.2.0.dist-info/RECORD
