Metadata-Version: 2.4
Name: dbos-openai-agents
Version: 0.2.0
Summary: DBOS integration for the OpenAI Agents SDK
Project-URL: Homepage, https://github.com/dbos-inc/dbos-openai
Project-URL: Repository, https://github.com/dbos-inc/dbos-openai
Author: DBOS, Inc.
License: MIT
License-File: LICENSE
Keywords: agents,dbos,durable,openai,workflow
Classifier: Development Status :: 4 - Beta
Classifier: License :: OSI Approved :: MIT License
Classifier: Programming Language :: Python :: 3.10
Classifier: Programming Language :: Python :: 3.11
Classifier: Programming Language :: Python :: 3.12
Classifier: Programming Language :: Python :: 3.13
Requires-Python: >=3.10
Requires-Dist: dbos>=2.10.0
Requires-Dist: openai-agents>=0.7.0
